{"title":"【歌詞翻譯】藤岡藤巻 - 息子よ","slug":"lyrics-fujioka-fujimaki-my-son","html":"<iframe width=\"720\" height=\"480\" src=\"https://www.youtube.com/embed/_XRJ8CYm3_8\" frameborder=\"0\" allow=\"accelerometer; autoplay; clipboard-write; encrypted-media; gyroscope; picture-in-picture\" allowfullscreen></iframe>\n\n<p>聽好了 兒子啊\n<br>只有一件事 要和你說\n<br>所謂人生就如同河流 是騙人的\n<br>人生才不是什麼河流 是沼澤</p>\n<p>聽好了 兒子啊\n<br>還有一件 要說的事\n<br>所謂要活的像滾動的石頭 是騙人的\n<br>人生就算放著不管 也會跌倒</p>\n<p>再來認真的跟你講吧 兒子啊\n<br>沒有比別人的不幸 還讓人開心的事情了\n<br>再怎麼說生活的辛勞 在這世間都是一樣的\n<br>常懷夢想於胸中活下去吧</p>\n<p>什麼的 別被這樣的話給騙了</p>\n<p>聽好了 兒子啊\n<br>所謂男人踏出家門一步之後\n<br>有七個敵人在等著你 是騙人的\n<br>真正的敵人 在家裡</p>\n<p>聽好了 兒子啊\n<br>好好的看著 所謂的人這個字\n<br>說什麼人與人相互扶持 根本是不可能的事\n<br>大的那一方會把小的這一方給壓下去了啊</p>\n<p>總有一天你也會成為父親吧\n<br>到那時再來了解就行了\n<br>這世上沒有比你還重要的東西\n<br>即使軟弱也好 長久的活下去吧</p>\n<p>而我那時的大小便 就拜托你處理了</p>\n<p>聽好了 兒子啊\n<br>確實你老爸是個沒出息的男人\n<br>不過人類的絕大多數 都是沒出息的傢伙哪\n<br>這麼想的話 你老爸還算不錯啦</p>\n<p>肯定不是最差勁的吧</p>\n<p>能不能這樣對我說呢 兒子啊</p>\n","date":"2017-04-06T12:18:10.000Z","printDate":"April 6, 2017","printReadingTime":"1 min read","tags":["Lyrics","Translate"]}